{
  "active": true,
  "connections": {
    "Get a task": {
      "main": [
        [
          {
            "node": "If task is in 📬Assigner Autre Section",
            "type": "main",
            "index": 0
          }
        ]
      ]
    },
    "If not a subtask": {
      "main": [
        [
          {
            "node": "Find ID of the department",
            "type": "main",
            "index": 0
          }
        ]
      ]
    },
    "Get ClickUpID of president": {
      "main": [
        [
          {
            "node": "Get ClickUp ID of Vice President",
            "type": "main",
            "index": 0
          }
        ]
      ]
    },
    "Update permissions": {
      "main": [
        [
          {
            "node": "Get name of targetted department",
            "type": "main",
            "index": 0
          }
        ],
        [
          {
            "node": "Update if creator is the VP of targeted department",
            "type": "main",
            "index": 0
          }
        ]
      ]
    },
    "Get ClickUp ID of Vice President": {
      "main": [
        [
          {
            "node": "Update permissions",
            "type": "main",
            "index": 0
          }
        ]
      ]
    },
    "ClickUp Trigger": {
      "main": [
        [
          {
            "node": "Get a task",
            "type": "main",
            "index": 0
          }
        ]
      ]
    },
    "If task is in 📬Assigner Autre Section": {
      "main": [
        [
          {
            "node": "If not a subtask",
            "type": "main",
            "index": 0
          }
        ]
      ]
    },
    "Find ID of the department": {
      "main": [
        [
          {
            "node": "Get ClickUpID of president",
            "type": "main",
            "index": 0
          }
        ]
      ]
    },
    "Get ClickUp ID of VP of Operations": {
      "main": [
        [
          {
            "node": "If VP of operations is vice president of task",
            "type": "main",
            "index": 0
          }
        ]
      ]
    },
    "If VP of operations is vice president of task": {
      "main": [
        [
          {
            "node": "Update permissions assuming VP is targetted department",
            "type": "main",
            "index": 0
          }
        ],
        [
          {
            "node": "If VP of operations is creating the task not in their department",
            "type": "main",
            "index": 0
          }
        ]
      ]
    },
    "Update permissions assuming VP is targetted department": {
      "main": [
        [],
        [
          {
            "node": "If VP of operations is creating the task in their department1",
            "type": "main",
            "index": 0
          }
        ]
      ]
    },
    "If VP of operations is creating the task not in their department": {
      "main": [
        [
          {
            "node": "Update permissions assuming VP made it NOT in their own department",
            "type": "main",
            "index": 0
          }
        ]
      ]
    },
    "Update permissions assuming VP made it in their own department": {
      "main": [
        []
      ]
    },
    "Update permissions assuming VP made it NOT in their own department": {
      "main": [
        []
      ]
    },
    "If VP of operations is creating the task in their department1": {
      "main": [
        [
          {
            "node": "Update permissions assuming VP made it in their own department",
            "type": "main",
            "index": 0
          }
        ]
      ]
    },
    "Update a task": {
      "main": [
        [
          {
            "node": "Add a task tag",
            "type": "main",
            "index": 0
          }
        ]
      ]
    },
    "Get name of targetted department": {
      "main": [
        [
          {
            "node": "Get name of VP",
            "type": "main",
            "index": 0
          }
        ]
      ]
    },
    "Get name of VP": {
      "main": [
        [
          {
            "node": "Update a task",
            "type": "main",
            "index": 0
          }
        ]
      ]
    },
    "Update if creator is the VP of targeted department": {
      "main": [
        [
          {
            "node": "Get name of targetted department",
            "type": "main",
            "index": 0
          }
        ],
        [
          {
            "node": "Update if president is making task",
            "type": "main",
            "index": 0
          }
        ]
      ]
    },
    "Update if president is making task": {
      "main": [
        [
          {
            "node": "Get name of targetted department",
            "type": "main",
            "index": 0
          }
        ]
      ]
    }
  },
  "createdAt": "2025-09-03T21:34:47.114Z",
  "id": "2NAYTiX9dlxdP5N5",
  "isArchived": false,
  "meta": {
    "templateCredsSetupCompleted": true
  },
  "name": "Assign Other Tasks - Private Task",
  "nodes": [
    {
      "parameters": {
        "authentication": "oAuth2",
        "operation": "get",
        "id": "={{ $json.task_id }}"
      },
      "type": "n8n-nodes-base.clickUp",
      "typeVersion": 1,
      "position": [
        -2432,
        48
      ],
      "id": "2de2de07-d88a-4d8e-9ef3-3224310aee59",
      "name": "Get a task",
      "credentials": {
        "clickUpOAuth2Api": {
          "id": "B6uymUDP8hJrRXiz",
          "name": "ClickUp account 2"
        }
      }
    },
    {
      "parameters": {
        "conditions": {
          "options": {
            "caseSensitive": true,
            "leftValue": "",
            "typeValidation": "strict",
            "version": 2
          },
          "conditions": [
            {
              "id": "edfec811-5d3f-46a6-8bba-f2553632eee4",
              "leftValue": "={{!$json[\"parent\"] }}",
              "rightValue": "",
              "operator": {
                "type": "boolean",
                "operation": "true",
                "singleValue": true
              }
            }
          ],
          "combinator": "and"
        },
        "options": {}
      },
      "type": "n8n-nodes-base.if",
      "typeVersion": 2.2,
      "position": [
        -1984,
        48
      ],
      "id": "3802da03-6cf3-432a-ae84-ee98bcd40f36",
      "name": "If not a subtask"
    },
    {
      "parameters": {
        "operation": "executeQuery",
        "query": "select \"ClickUpID\" as \"PresidentClickUpID\"from \"Members\" m JOIN \"MemberRole\" mr ON m.\"id\"=mr.\"memberID\" where mr.\"roleID\"=3;",
        "options": {}
      },
      "type": "n8n-nodes-base.postgres",
      "typeVersion": 2.6,
      "position": [
        -1536,
        48
      ],
      "id": "6b5b007b-0bc0-4171-ae50-ed9008b19aae",
      "name": "Get ClickUpID of president",
      "credentials": {
        "postgres": {
          "id": "ucbPPN2ixG5PoGk4",
          "name": "Postgres account"
        }
      }
    },
    {
      "parameters": {
        "method": "PATCH",
        "url": "=https://api.clickup.com/api/v3/workspaces/{{ $('Get a task').item.json.team_id }}/task/{{ $('Get a task').item.json.id }}/acls",
        "authentication": "predefinedCredentialType",
        "nodeCredentialType": "clickUpOAuth2Api",
        "sendBody": true,
        "specifyBody": "json",
        "jsonBody": "={\n  \"entries\": [\n    {\n      \"id\": \"{{ $('Get ClickUpID of president').item.json.PresidentClickUpID }}\",\n      \"kind\": \"user\",\n      \"permission_level\": 5\n    },\n    {\n      \"id\": \"{{ $json.VicePresidentClickUpID }}\",\n      \"kind\": \"user\",\n      \"permission_level\": 5\n    },\n    {\n      \"id\": \"{{ $('Get a task').item.json.creator.id }}\",\n      \"kind\": \"user\",\n      \"permission_level\": 5\n    }\n  ],\n  \"private\": true\n}\n",
        "options": {}
      },
      "type": "n8n-nodes-base.httpRequest",
      "typeVersion": 4.2,
      "position": [
        -1088,
        48
      ],
      "id": "75bc9639-0872-4508-8e77-242d43baae76",
      "name": "Update permissions",
      "alwaysOutputData": false,
      "retryOnFail": false,
      "credentials": {
        "clickUpOAuth2Api": {
          "id": "B6uymUDP8hJrRXiz",
          "name": "ClickUp account 2"
        }
      },
      "onError": "continueErrorOutput"
    },
    {
      "parameters": {
        "operation": "executeQuery",
        "query": "select \"ClickUpID\" as \"VicePresidentClickUpID\" from \"Members\" m JOIN \"MemberDepartment\" md ON m.\"id\"=md.\"memberID\" where md.\"departmentID\"={{ $('Find ID of the department').item.json.DepartmentID }};",
        "options": {}
      },
      "type": "n8n-nodes-base.postgres",
      "typeVersion": 2.6,
      "position": [
        -1312,
        48
      ],
      "id": "9806b615-4641-4901-9f25-d9cd1695b323",
      "name": "Get ClickUp ID of Vice President",
      "credentials": {
        "postgres": {
          "id": "ucbPPN2ixG5PoGk4",
          "name": "Postgres account"
        }
      }
    },
    {
      "parameters": {
        "authentication": "oAuth2",
        "team": "90131880769",
        "events": [
          "taskCreated"
        ],
        "filters": {}
      },
      "type": "n8n-nodes-base.clickUpTrigger",
      "typeVersion": 1,
      "position": [
        -2656,
        48
      ],
      "id": "125c009e-9f29-40fd-80f6-c5fda370dae5",
      "name": "ClickUp Trigger",
      "webhookId": "a0082970-0ae6-4e9b-a442-dae883a73c77",
      "credentials": {
        "clickUpOAuth2Api": {
          "id": "B6uymUDP8hJrRXiz",
          "name": "ClickUp account 2"
        }
      }
    },
    {
      "parameters": {
        "conditions": {
          "options": {
            "caseSensitive": true,
            "leftValue": "",
            "typeValidation": "strict",
            "version": 2
          },
          "conditions": [
            {
              "id": "c670f636-c429-4bc7-93a4-145d374f1cff",
              "leftValue": "={{ $json.folder.name }}",
              "rightValue": "📬Assigner Autre Section",
              "operator": {
                "type": "string",
                "operation": "equals",
                "name": "filter.operator.equals"
              }
            }
          ],
          "combinator": "and"
        },
        "options": {}
      },
      "type": "n8n-nodes-base.if",
      "typeVersion": 2.2,
      "position": [
        -2208,
        48
      ],
      "id": "29389e15-e64c-4686-b1d2-924d6a4be4b8",
      "name": "If task is in 📬Assigner Autre Section"
    },
    {
      "parameters": {
        "operation": "executeQuery",
        "query": "select id as \"DepartmentID\" from \"Department\" where \"ClickUpAssignOtherListID\"={{ $('Get a task').item.json.list.id }}",
        "options": {}
      },
      "type": "n8n-nodes-base.postgres",
      "typeVersion": 2.6,
      "position": [
        -1760,
        48
      ],
      "id": "74a4adc5-2eaf-471e-9a6c-c0729ff69ad6",
      "name": "Find ID of the department",
      "credentials": {
        "postgres": {
          "id": "ucbPPN2ixG5PoGk4",
          "name": "Postgres account"
        }
      }
    },
    {
      "parameters": {
        "operation": "executeQuery",
        "query": "select \"ClickUpID\" as \"OperationsVPClickUpID\" from \"Members\" m join \"MemberRole\" mr on m.\"id\"=mr.\"memberID\" join \"MemberDepartment\" md on m.\"id\"=md.\"memberID\" join \"Department\" d on d.\"id\"=\"departmentID\" join \"Role\" r on r.\"id\"=\"roleID\" where \"departmentName\"='Opérations' and \"roleName\"='VP';",
        "options": {}
      },
      "type": "n8n-nodes-base.postgres",
      "typeVersion": 2.6,
      "position": [
        -2656,
        512
      ],
      "id": "7699224e-8173-49a3-90e7-853197fe51a3",
      "name": "Get ClickUp ID of VP of Operations",
      "credentials": {
        "postgres": {
          "id": "ucbPPN2ixG5PoGk4",
          "name": "Postgres account"
        }
      }
    },
    {
      "parameters": {
        "conditions": {
          "options": {
            "caseSensitive": true,
            "leftValue": "",
            "typeValidation": "loose",
            "version": 2
          },
          "conditions": [
            {
              "id": "fcc5d36e-faab-48e8-95f4-ebd52888d0da",
              "leftValue": "={{ $('Get ClickUp ID of Vice President').item.json.VicePresidentClickUpID }}",
              "rightValue": "={{ $json.OperationsVPClickUpID }}",
              "operator": {
                "type": "string",
                "operation": "equals",
                "name": "filter.operator.equals"
              }
            }
          ],
          "combinator": "or"
        },
        "looseTypeValidation": true,
        "options": {}
      },
      "type": "n8n-nodes-base.if",
      "typeVersion": 2.2,
      "position": [
        -2432,
        512
      ],
      "id": "1dd9080f-0752-4204-9642-81c7977ee1ca",
      "name": "If VP of operations is vice president of task"
    },
    {
      "parameters": {
        "method": "PATCH",
        "url": "=https://api.clickup.com/api/v3/workspaces/{{ $('Get a task').item.json.team_id }}/task/{{ $('Get a task').item.json.id }}/acls",
        "authentication": "predefinedCredentialType",
        "nodeCredentialType": "clickUpOAuth2Api",
        "sendBody": true,
        "specifyBody": "json",
        "jsonBody": "={\n  \"entries\": [\n    {\n      \"id\": \"{{ $('Get ClickUpID of president').item.json.PresidentClickUpID }}\",\n      \"kind\": \"user\",\n      \"permission_level\": 5\n    },\n    {\n      \"id\": \"{{ $('Get a task').item.json.creator.id }}\",\n      \"kind\": \"user\",\n      \"permission_level\": 5\n    }\n  ],\n  \"private\": true\n}\n",
        "options": {}
      },
      "type": "n8n-nodes-base.httpRequest",
      "typeVersion": 4.2,
      "position": [
        -2208,
        416
      ],
      "id": "b80a3b7f-6497-4976-a5f1-c341c4f48d23",
      "name": "Update permissions assuming VP is targetted department",
      "alwaysOutputData": false,
      "retryOnFail": false,
      "credentials": {
        "clickUpOAuth2Api": {
          "id": "B6uymUDP8hJrRXiz",
          "name": "ClickUp account 2"
        }
      },
      "onError": "continueErrorOutput"
    },
    {
      "parameters": {
        "conditions": {
          "options": {
            "caseSensitive": true,
            "leftValue": "",
            "typeValidation": "loose",
            "version": 2
          },
          "conditions": [
            {
              "id": "83dc20a4-747c-43b5-a7e4-bf83b12f3005",
              "leftValue": "={{ Number($('Get a task').item.json.creator.id) }}",
              "rightValue": "={{ $json.OperationsVPClickUpID }}",
              "operator": {
                "type": "string",
                "operation": "equals",
                "name": "filter.operator.equals"
              }
            },
            {
              "id": "f2734114-6cee-464b-b408-d9ee220bd9e6",
              "leftValue": "={{ Number($('Find ID of the department').item.json.DepartmentID) }}",
              "rightValue": 7,
              "operator": {
                "type": "number",
                "operation": "notEquals"
              }
            }
          ],
          "combinator": "and"
        },
        "looseTypeValidation": true,
        "options": {}
      },
      "type": "n8n-nodes-base.if",
      "typeVersion": 2.2,
      "position": [
        -2208,
        608
      ],
      "id": "4095df0f-2cd9-4782-ac0a-13c5cb4443e0",
      "name": "If VP of operations is creating the task not in their department"
    },
    {
      "parameters": {
        "method": "PATCH",
        "url": "=https://api.clickup.com/api/v3/workspaces/{{ $('Get a task').item.json.team_id }}/task/{{ $('Get a task').item.json.id }}/acls",
        "authentication": "predefinedCredentialType",
        "nodeCredentialType": "clickUpOAuth2Api",
        "sendBody": true,
        "specifyBody": "json",
        "jsonBody": "={\n  \"entries\": [\n    {\n      \"id\": \"{{ $('Get ClickUpID of president').item.json.PresidentClickUpID }}\",\n      \"kind\": \"user\",\n      \"permission_level\": 5\n    }\n  ],\n  \"private\": true\n}\n",
        "options": {}
      },
      "type": "n8n-nodes-base.httpRequest",
      "typeVersion": 4.2,
      "position": [
        -1760,
        416
      ],
      "id": "0ed255a0-217e-4524-b297-00ab3476af5d",
      "name": "Update permissions assuming VP made it in their own department",
      "alwaysOutputData": false,
      "retryOnFail": false,
      "credentials": {
        "clickUpOAuth2Api": {
          "id": "B6uymUDP8hJrRXiz",
          "name": "ClickUp account 2"
        }
      },
      "onError": "continueErrorOutput"
    },
    {
      "parameters": {
        "method": "PATCH",
        "url": "=https://api.clickup.com/api/v3/workspaces/{{ $('Get a task').item.json.team_id }}/task/{{ $('Get a task').item.json.id }}/acls",
        "authentication": "predefinedCredentialType",
        "nodeCredentialType": "clickUpOAuth2Api",
        "sendBody": true,
        "specifyBody": "json",
        "jsonBody": "={\n  \"entries\": [\n    {\n      \"id\": \"{{ $('Get ClickUpID of president').item.json.PresidentClickUpID }}\",\n      \"kind\": \"user\",\n      \"permission_level\": 5\n    },\n    {\n      \"id\": \"{{ $('Get ClickUp ID of Vice President').item.json.VicePresidentClickUpID }}\",\n      \"kind\": \"user\",\n      \"permission_level\": 5\n    }\n  ],\n  \"private\": true\n}\n",
        "options": {}
      },
      "type": "n8n-nodes-base.httpRequest",
      "typeVersion": 4.2,
      "position": [
        -1984,
        608
      ],
      "id": "162fc815-aa96-4124-a673-a1f1ff291009",
      "name": "Update permissions assuming VP made it NOT in their own department",
      "alwaysOutputData": false,
      "retryOnFail": false,
      "credentials": {
        "clickUpOAuth2Api": {
          "id": "B6uymUDP8hJrRXiz",
          "name": "ClickUp account 2"
        }
      },
      "onError": "continueErrorOutput"
    },
    {
      "parameters": {
        "conditions": {
          "options": {
            "caseSensitive": true,
            "leftValue": "",
            "typeValidation": "loose",
            "version": 2
          },
          "conditions": [
            {
              "id": "83dc20a4-747c-43b5-a7e4-bf83b12f3005",
              "leftValue": "={{ Number($('Get a task').item.json.creator.id) }}",
              "rightValue": "={{ $json.OperationsVPClickUpID }}",
              "operator": {
                "type": "string",
                "operation": "equals",
                "name": "filter.operator.equals"
              }
            },
            {
              "id": "f2734114-6cee-464b-b408-d9ee220bd9e6",
              "leftValue": "={{ Number($('Find ID of the department').item.json.DepartmentID) }}",
              "rightValue": 7,
              "operator": {
                "type": "number",
                "operation": "equals"
              }
            }
          ],
          "combinator": "and"
        },
        "looseTypeValidation": true,
        "options": {}
      },
      "type": "n8n-nodes-base.if",
      "typeVersion": 2.2,
      "position": [
        -1984,
        416
      ],
      "id": "98262de4-6563-4765-90ef-891af1736b18",
      "name": "If VP of operations is creating the task in their department1"
    },
    {
      "parameters": {
        "authentication": "oAuth2",
        "operation": "update",
        "id": "={{ $('Get a task').item.json.id }}",
        "updateFields": {
          "addAssignees": "={{ $('Get ClickUp ID of Vice President').item.json.VicePresidentClickUpID }}",
          "content": "=Département cible: {{ $('Get name of targetted department').item.json.departmentName }}\nVice-président: {{ $json.VPname }}\nCréateur de la tâche: {{ $('Get a task').item.json.creator.username }}\n",
          "name": "=📬 {{ $('Get a task').item.json.name }}"
        }
      },
      "type": "n8n-nodes-base.clickUp",
      "typeVersion": 1,
      "position": [
        32,
        48
      ],
      "id": "e33a921b-f1dc-4b87-9234-382f87f6a75d",
      "name": "Update a task",
      "credentials": {
        "clickUpOAuth2Api": {
          "id": "B6uymUDP8hJrRXiz",
          "name": "ClickUp account 2"
        }
      }
    },
    {
      "parameters": {
        "operation": "executeQuery",
        "query": "select \"departmentName\" from \"Department\" where \"id\"={{ $('Find ID of the department').item.json.DepartmentID }}",
        "options": {}
      },
      "type": "n8n-nodes-base.postgres",
      "typeVersion": 2.6,
      "position": [
        -416,
        48
      ],
      "id": "78f33673-3b0f-46cd-abf7-3baee04d1afa",
      "name": "Get name of targetted department",
      "credentials": {
        "postgres": {
          "id": "ucbPPN2ixG5PoGk4",
          "name": "Postgres account"
        }
      }
    },
    {
      "parameters": {
        "operation": "executeQuery",
        "query": "select \"name\" as \"VPname\" from \"Members\" where \"ClickUpID\"={{ $('Get ClickUp ID of Vice President').item.json.VicePresidentClickUpID }}",
        "options": {}
      },
      "type": "n8n-nodes-base.postgres",
      "typeVersion": 2.6,
      "position": [
        -192,
        48
      ],
      "id": "8bee0116-9eb9-4941-822f-bb274dfb8136",
      "name": "Get name of VP",
      "credentials": {
        "postgres": {
          "id": "ucbPPN2ixG5PoGk4",
          "name": "Postgres account"
        }
      }
    },
    {
      "parameters": {
        "authentication": "oAuth2",
        "resource": "taskTag",
        "taskId": "={{ $json.id }}",
        "tagName": "autresec",
        "additionalFields": {}
      },
      "type": "n8n-nodes-base.clickUp",
      "typeVersion": 1,
      "position": [
        256,
        48
      ],
      "id": "9eb6adc6-6b6b-4561-bb41-ca5e6a215c55",
      "name": "Add a task tag",
      "credentials": {
        "clickUpOAuth2Api": {
          "id": "B6uymUDP8hJrRXiz",
          "name": "ClickUp account 2"
        }
      }
    },
    {
      "parameters": {
        "method": "PATCH",
        "url": "=https://api.clickup.com/api/v3/workspaces/{{ $('Get a task').item.json.team_id }}/task/{{ $('Get a task').item.json.id }}/acls",
        "authentication": "predefinedCredentialType",
        "nodeCredentialType": "clickUpOAuth2Api",
        "sendBody": true,
        "specifyBody": "json",
        "jsonBody": "={\n  \"entries\": [\n    {\n      \"id\": \"{{ $('Get ClickUpID of president').item.json.PresidentClickUpID }}\",\n      \"kind\": \"user\",\n      \"permission_level\": 5\n    },\n    {\n      \"id\": \"{{ $json.VicePresidentClickUpID }}\",\n      \"kind\": \"user\",\n      \"permission_level\": 5\n    }\n  ],\n  \"private\": true\n}\n",
        "options": {}
      },
      "type": "n8n-nodes-base.httpRequest",
      "typeVersion": 4.2,
      "position": [
        -864,
        120
      ],
      "id": "25c37f91-d682-46cf-b1d2-f9924a12293e",
      "name": "Update if creator is the VP of targeted department",
      "alwaysOutputData": false,
      "retryOnFail": false,
      "credentials": {
        "clickUpOAuth2Api": {
          "id": "B6uymUDP8hJrRXiz",
          "name": "ClickUp account 2"
        }
      },
      "onError": "continueErrorOutput"
    },
    {
      "parameters": {
        "method": "PATCH",
        "url": "=https://api.clickup.com/api/v3/workspaces/{{ $('Get a task').item.json.team_id }}/task/{{ $('Get a task').item.json.id }}/acls",
        "authentication": "predefinedCredentialType",
        "nodeCredentialType": "clickUpOAuth2Api",
        "sendBody": true,
        "specifyBody": "json",
        "jsonBody": "={\n  \"entries\": [\n    {\n      \"id\": \"{{ $('Get ClickUpID of president').item.json.PresidentClickUpID }}\",\n      \"kind\": \"user\",\n      \"permission_level\": 5\n    },\n    {\n      \"id\": \"{{ $json.VicePresidentClickUpID }}\",\n      \"kind\": \"user\",\n      \"permission_level\": 5\n    }\n  ],\n  \"private\": true\n}\n",
        "options": {}
      },
      "type": "n8n-nodes-base.httpRequest",
      "typeVersion": 4.2,
      "position": [
        -640,
        192
      ],
      "id": "c4f7cd27-5cae-4d51-bed9-506a90049348",
      "name": "Update if president is making task",
      "alwaysOutputData": false,
      "retryOnFail": false,
      "credentials": {
        "clickUpOAuth2Api": {
          "id": "B6uymUDP8hJrRXiz",
          "name": "ClickUp account 2"
        }
      },
      "onError": "continueErrorOutput"
    }
  ],
  "origin": "n8n",
  "pinData": {},
  "repo": {
    "owner": "operationspolyai",
    "name": "n8n-backup"
  },
  "settings": {
    "executionOrder": "v1"
  },
  "shared": [
    {
      "createdAt": "2025-09-03T21:34:47.127Z",
      "updatedAt": "2025-09-03T21:34:47.127Z",
      "role": "workflow:owner",
      "workflowId": "2NAYTiX9dlxdP5N5",
      "projectId": "NulObFSfFSWs7ssm"
    }
  ],
  "staticData": {
    "node:ClickUp Trigger": {
      "webhookId": "e6772f24-e5c3-40a3-b7d3-06dbac0fb9a2",
      "secret": "NVR5VN2FM33FYHQMEEF1DKKGSJWF7X6OQI87FOYPOY94XPEK7YV2A37FLNWOV0WW"
    }
  },
  "tags": [],
  "triggerCount": 1,
  "updatedAt": "2025-09-14T21:26:03.000Z",
  "versionId": "9e7b9595-9195-401f-91da-6888c5a9ad18"
}